klr/README.md
klr/__init__.py
klr/_cli.py
klr/ast_common.h
klr/ast_file.h
klr/ast_nki.h
klr/ast_nki.py
klr/ast_python.h
klr/ast_python_core.h
klr/cbor.c
klr/cbor.h
klr/cbor_test.c
klr/frontend.c
klr/frontend.cpython-312-x86_64-linux-gnu.so
klr/frontend.h
klr/gather.c
klr/klr.bin
klr/peg_parser.c
klr/region.c
klr/region.h
klr/serde.c
klr/serde_common.c
klr/serde_common.h
klr/serde_file.c
klr/serde_file.h
klr/serde_nki.c
klr/serde_nki.h
klr/serde_python_core.c
klr/serde_python_core.h
klr/simplify.c
klr/simplify_test.c
klr/stdc.h
klr/topy_nki.c
klr/topy_nki.h
klr/peg_parser/README.md
klr/peg_parser/Tokens
klr/peg_parser/action_helpers.c
klr/peg_parser/ast_python.c
klr/peg_parser/compat.c
klr/peg_parser/parser.c
klr/peg_parser/pegen.c
klr/peg_parser/python.gram
klr/peg_parser/string_parser.c
klr/peg_parser/token.c
klr/peg_parser/tokenizer.c
klr_lang-0.0.12.dist-info/LICENSE
klr_lang-0.0.12.dist-info/METADATA
klr_lang-0.0.12.dist-info/WHEEL
klr_lang-0.0.12.dist-info/entry_points.txt
klr_lang-0.0.12.dist-info/top_level.txt
klr_lang-0.0.12.dist-info/RECORD
