Metadata-Version: 2.1
Name: klr-lang
Version: 0.0.12
Summary: Intermediate langauge for tensor compilers
Author-email: Paul Govereau <govereau@amazon.com>, Sean McLaughlin <seanmcl@amazon.com>
License: Apache-2.0
Project-URL: Repository, https://github.com/leanprover/KLR
Keywords: trainium,tpu,pallas,triton,gpu
Requires-Python: <3.13,>=3.9
License-File: LICENSE
Requires-Dist: numpy
